PyMicrophone/__init__.py
PyMicrophone/microphone.py
PyMicrophone/player.py
PyMicrophone-1.1.2.dist-info/METADATA
PyMicrophone-1.1.2.dist-info/WHEEL
PyMicrophone-1.1.2.dist-info/top_level.txt
PyMicrophone-1.1.2.dist-info/RECORD
