Metadata-Version: 2.1
Name: PyMicrophone
Version: 1.1.2
Summary: 使用python录音, 播放wav文件
Home-page: http://frozenleaves.cn/pymicrophone
Author: 幽若
Author-email: 914814442@qq.com
License: UNKNOWN
Platform: UNKNOWN
Classifier: Programming Language :: Python :: 3
Classifier: License :: OSI Approved :: MIT License
Classifier: Operating System :: OS Independent
Requires-Python: >=3.7
Requires-Dist: PyAudio (>=0.2.11)
